pingshui_rhyme/__init__.py
pingshui_rhyme/classifier.py
pingshui_rhyme/poem_structure_checker.py
pingshui_rhyme/rhymechecker.py
pingshui_rhyme/scraper.py
pingshui_rhyme/data/organized_ping_ze_rhyme_dict.json
pingshui_rhyme-0.20.dist-info/licenses/LICENSE
tests/__init__.py
tests/test_classifier.py
tests/test_poem_structure.py
tests/test_rhyme.py
pingshui_rhyme-0.20.dist-info/METADATA
pingshui_rhyme-0.20.dist-info/WHEEL
pingshui_rhyme-0.20.dist-info/top_level.txt
pingshui_rhyme-0.20.dist-info/RECORD
