Metadata-Version: 2.4
Name: pingshui-rhyme
Version: 0.20
Summary: A Python package for classifying Chinese characters phonologically based on the Middle Chinese Pingshui rhyme scheme
Home-page: https://github.com/rbnyng/pingshui_rhyme
Author: rbnyng
Author-email: 
Classifier: Programming Language :: Python :: 3
Classifier: License :: OSI Approved :: MIT License
Classifier: Operating System :: OS Independent
Requires-Python: >=3.6
License-File: LICENSE
Requires-Dist: beautifulsoup4
Requires-Dist: requests
Dynamic: author
Dynamic: classifier
Dynamic: description
Dynamic: description-content-type
Dynamic: home-page
Dynamic: license-file
Dynamic: requires-dist
Dynamic: requires-python
Dynamic: summary
